prefix_adder.v


module and2 (input wire i0, i1, output wire o);
	assign o = i0 & i1;
endmodule

module or2 (input wire i0, i1, output wire o);
	assign o = i0 | i1;
endmodule

module xor2 (input wire i0, i1, output wire o);
	assign o = i0 ^ i1;
endmodule

module xor3 (input wire i0, i1, i2, output wire o);
	wire temp;
	xor2 xor2_0 (i0, i1, temp);
	xor2 xor2_1 (i2, temp, o);
endmodule

module prop_gen(input wire x,y, output wire p,g);
	or2 o(x,y,p);
	and2 a(x,y,g);
endmodule

module carry(input wire p1,p0,g1,g0, output wire p, g);
	wire t;
	and2 a1(p1,p0,p);
	and2 a2(p1,g0,t);
	or2 o2(t,g1,g);
endmodule

module prefixAdd(input wire [7:0]a,b, input wire cin, output wire [7:0] S);
	wire p[7:0],g[7:0];
	wire cp[7:0],cg[7:0];
	wire cp21,cg21,cp43,cg43,cp54,cg54,cp65,cg65,cp64,cg64;

	prop_gen p_0(a[0],b[0],p[0],g[0]);
	prop_gen p_1(a[1],b[1],p[1],g[1]);
	prop_gen p_2(a[2],b[2],p[2],g[2]);
	prop_gen p_3(a[3],b[3],p[3],g[3]);
	prop_gen p_4(a[4],b[4],p[4],g[4]);
	prop_gen p_5(a[5],b[5],p[5],g[5]);
	prop_gen p_6(a[6],b[6],p[6],g[6]);
	prop_gen p_7(a[7],b[7],p[7],g[7]);

	assign cp[0] = 1'b0;
	assign cg[0] = 1'b0;

	carry c1(p[0],1'b0,g[0],cin,cp[1],cg[1]);
	carry c3_0(p[2],p[1],g[2],g[1],cp21,cg21);
	carry c5_0(p[4],p[3],g[4],g[3],cp43,cg43);
	carry c7_0(p[6],p[5],g[6],g[5],cp65,cg65);

	carry c2(p[1],cp[1],g[1],cg[1],cp[2],cg[2]);
	carry c3_1(cp21,cp[1],cg21,cg[1],cp[3],cg[3]);
	carry c6_0(p[5],cp43,g[5],cg43,cp54,cg54);
	carry c7_1(cp65,cp43,cg65,cg43,cp64,cg64);

	carry c4(p[3],cp[3],g[3],cg[3],cp[4],cg[4]);
	carry c5_1(cp43,cp[3],cg43,cg[3],cp[5],cg[5]);
	carry c6_1(cp54,cp[3],cg54,cg[3],cp[6],cg[6]);
	carry c7_2(cp64,cp[3],cg64,cg[3],cp[7],cg[7]);

	xor3 s0(a[0],b[0],cin,S[0]);
	xor3 s1(a[1],b[1],cg[1],S[1]);
	xor3 s2(a[2],b[2],cg[2],S[2]);
	xor3 s3(a[3],b[3],cg[3],S[3]);
	xor3 s4(a[4],b[4],cg[4],S[4]);
	xor3 s5(a[5],b[5],cg[5],S[5]);
	xor3 s6(a[6],b[6],cg[6],S[6]);
	xor3 s7(a[7],b[7],cg[7],S[7]);
endmodule

tb_prefix_adder.v
module tb_prefix;
reg [7:0] t_a,t_b;
reg t_cin;
wire [7:0] t_S;
initial begin $dumpfile("dump.vcd"); $dumpvars(0, tb_prefix); end
prefixAdd pra (.a(t_a), .b(t_b), .cin(t_cin), .S(t_S));
initial
begin
	t_a [7:0] = 8'b00000000; //0
	t_b [7:0] = 8'b00101001; //41
	t_cin = 1'b0;
	#5
	t_a [7:0] = 8'b01100100; //100
	t_b [7:0] = 8'b00011000; //24
	t_cin = 1'b0;
	#5
	t_a [7:0] = 8'b00010100; //20
	t_b [7:0] = 8'b10110010; //178
	t_cin = 1'b0;
	#5
	t_a [7:0] = 8'b00100001; //33
	t_b [7:0] = 8'b01001011; //75
	t_cin = 1'b0;
	#5
	t_a [7:0] = 8'b01100100; //100
	t_b [7:0] = 8'b00110010; //50
	t_cin = 1'b0;
	#5
	t_a [7:0] = 8'b01011010; //90
	t_b [7:0] = 8'b00101000; //40
	t_cin = 1'b0;
	#5
	t_a [7:0] = 8'b10110001; //177
	t_b [7:0] = 8'b00110110; //54
	t_cin = 1'b0;
	#5
	t_a [7:0] = 8'b01011010; //90
	t_b [7:0] = 8'b00111100; //60
	t_cin = 1'b0;
	#5
	t_a [7:0] = 8'b00011000; //24
	t_b [7:0] = 8'b00101011; //43
	t_cin = 1'b0;
	#10
	t_a [7:0] = 8'b00000000;
	t_b [7:0] = 8'b00000001;
	t_cin = 1'b0;
end
endmodule

dump.vcd
$date
	Mon Nov 22 14:51:04 2021
$end
$version
	Icarus Verilog
$end
$timescale
	1s
$end
$scope module tb_prefix $end
$var wire 8 ! t_S [7:0] $end
$var reg 8 " t_a [7:0] $end
$var reg 8 # t_b [7:0] $end
$var reg 1 $ t_cin $end
$scope module pra $end
$var wire 8 % a [7:0] $end
$var wire 8 & b [7:0] $end
$var wire 1 $ cin $end
$var wire 1 ' cp65 $end
$var wire 1 ( cp64 $end
$var wire 1 ) cp54 $end
$var wire 1 * cp43 $end
$var wire 1 + cp21 $end
$var wire 1 , cg65 $end
$var wire 1 - cg64 $end
$var wire 1 . cg54 $end
$var wire 1 / cg43 $end
$var wire 1 0 cg21 $end
$var wire 8 1 S [7:0] $end
$scope module c1 $end
$var wire 1 $ g0 $end
$var wire 1 2 p0 $end
$var wire 1 3 t $end
$var wire 1 4 p1 $end
$var wire 1 5 p $end
$var wire 1 6 g1 $end
$var wire 1 7 g $end
$scope module a1 $end
$var wire 1 2 i1 $end
$var wire 1 5 o $end
$var wire 1 4 i0 $end
$upscope $end
$scope module a2 $end
$var wire 1 $ i1 $end
$var wire 1 3 o $end
$var wire 1 4 i0 $end
$upscope $end
$scope module o2 $end
$var wire 1 3 i0 $end
$var wire 1 7 o $end
$var wire 1 6 i1 $end
$upscope $end
$upscope $end
$scope module c2 $end
$var wire 1 7 g0 $end
$var wire 1 5 p0 $end
$var wire 1 8 t $end
$var wire 1 9 p1 $end
$var wire 1 : p $end
$var wire 1 ; g1 $end
$var wire 1 < g $end
$scope module a1 $end
$var wire 1 5 i1 $end
$var wire 1 : o $end
$var wire 1 9 i0 $end
$upscope $end
$scope module a2 $end
$var wire 1 7 i1 $end
$var wire 1 8 o $end
$var wire 1 9 i0 $end
$upscope $end
$scope module o2 $end
$var wire 1 8 i0 $end
$var wire 1 < o $end
$var wire 1 ; i1 $end
$upscope $end
$upscope $end
$scope module c3_0 $end
$var wire 1 = t $end
$var wire 1 > p1 $end
$var wire 1 9 p0 $end
$var wire 1 + p $end
$var wire 1 ? g1 $end
$var wire 1 ; g0 $end
$var wire 1 0 g $end
$scope module a1 $end
$var wire 1 + o $end
$var wire 1 9 i1 $end
$var wire 1 > i0 $end
$upscope $end
$scope module a2 $end
$var wire 1 = o $end
$var wire 1 ; i1 $end
$var wire 1 > i0 $end
$upscope $end
$scope module o2 $end
$var wire 1 = i0 $end
$var wire 1 0 o $end
$var wire 1 ? i1 $end
$upscope $end
$upscope $end
$scope module c3_1 $end
$var wire 1 7 g0 $end
$var wire 1 0 g1 $end
$var wire 1 5 p0 $end
$var wire 1 + p1 $end
$var wire 1 @ t $end
$var wire 1 A p $end
$var wire 1 B g $end
$scope module a1 $end
$var wire 1 + i0 $end
$var wire 1 5 i1 $end
$var wire 1 A o $end
$upscope $end
$scope module a2 $end
$var wire 1 + i0 $end
$var wire 1 7 i1 $end
$var wire 1 @ o $end
$upscope $end
$scope module o2 $end
$var wire 1 @ i0 $end
$var wire 1 0 i1 $end
$var wire 1 B o $end
$upscope $end
$upscope $end
$scope module c4 $end
$var wire 1 B g0 $end
$var wire 1 A p0 $end
$var wire 1 C t $end
$var wire 1 D p1 $end
$var wire 1 E p $end
$var wire 1 F g1 $end
$var wire 1 G g $end
$scope module a1 $end
$var wire 1 A i1 $end
$var wire 1 E o $end
$var wire 1 D i0 $end
$upscope $end
$scope module a2 $end
$var wire 1 B i1 $end
$var wire 1 C o $end
$var wire 1 D i0 $end
$upscope $end
$scope module o2 $end
$var wire 1 C i0 $end
$var wire 1 G o $end
$var wire 1 F i1 $end
$upscope $end
$upscope $end
$scope module c5_0 $end
$var wire 1 H t $end
$var wire 1 I p1 $end
$var wire 1 D p0 $end
$var wire 1 * p $end
$var wire 1 J g1 $end
$var wire 1 F g0 $end
$var wire 1 / g $end
$scope module a1 $end
$var wire 1 * o $end
$var wire 1 D i1 $end
$var wire 1 I i0 $end
$upscope $end
$scope module a2 $end
$var wire 1 H o $end
$var wire 1 F i1 $end
$var wire 1 I i0 $end
$upscope $end
$scope module o2 $end
$var wire 1 H i0 $end
$var wire 1 / o $end
$var wire 1 J i1 $end
$upscope $end
$upscope $end
$scope module c5_1 $end
$var wire 1 B g0 $end
$var wire 1 / g1 $end
$var wire 1 A p0 $end
$var wire 1 * p1 $end
$var wire 1 K t $end
$var wire 1 L p $end
$var wire 1 M g $end
$scope module a1 $end
$var wire 1 * i0 $end
$var wire 1 A i1 $end
$var wire 1 L o $end
$upscope $end
$scope module a2 $end
$var wire 1 * i0 $end
$var wire 1 B i1 $end
$var wire 1 K o $end
$upscope $end
$scope module o2 $end
$var wire 1 K i0 $end
$var wire 1 / i1 $end
$var wire 1 M o $end
$upscope $end
$upscope $end
$scope module c6_0 $end
$var wire 1 / g0 $end
$var wire 1 * p0 $end
$var wire 1 N t $end
$var wire 1 O p1 $end
$var wire 1 ) p $end
$var wire 1 P g1 $end
$var wire 1 . g $end
$scope module a1 $end
$var wire 1 * i1 $end
$var wire 1 ) o $end
$var wire 1 O i0 $end
$upscope $end
$scope module a2 $end
$var wire 1 / i1 $end
$var wire 1 N o $end
$var wire 1 O i0 $end
$upscope $end
$scope module o2 $end
$var wire 1 N i0 $end
$var wire 1 . o $end
$var wire 1 P i1 $end
$upscope $end
$upscope $end
$scope module c6_1 $end
$var wire 1 B g0 $end
$var wire 1 . g1 $end
$var wire 1 A p0 $end
$var wire 1 ) p1 $end
$var wire 1 Q t $end
$var wire 1 R p $end
$var wire 1 S g $end
$scope module a1 $end
$var wire 1 ) i0 $end
$var wire 1 A i1 $end
$var wire 1 R o $end
$upscope $end
$scope module a2 $end
$var wire 1 ) i0 $end
$var wire 1 B i1 $end
$var wire 1 Q o $end
$upscope $end
$scope module o2 $end
$var wire 1 Q i0 $end
$var wire 1 . i1 $end
$var wire 1 S o $end
$upscope $end
$upscope $end
$scope module c7_0 $end
$var wire 1 T t $end
$var wire 1 U p1 $end
$var wire 1 O p0 $end
$var wire 1 ' p $end
$var wire 1 V g1 $end
$var wire 1 P g0 $end
$var wire 1 , g $end
$scope module a1 $end
$var wire 1 ' o $end
$var wire 1 O i1 $end
$var wire 1 U i0 $end
$upscope $end
$scope module a2 $end
$var wire 1 T o $end
$var wire 1 P i1 $end
$var wire 1 U i0 $end
$upscope $end
$scope module o2 $end
$var wire 1 T i0 $end
$var wire 1 , o $end
$var wire 1 V i1 $end
$upscope $end
$upscope $end
$scope module c7_1 $end
$var wire 1 / g0 $end
$var wire 1 , g1 $end
$var wire 1 * p0 $end
$var wire 1 ' p1 $end
$var wire 1 W t $end
$var wire 1 ( p $end
$var wire 1 - g $end
$scope module a1 $end
$var wire 1 ' i0 $end
$var wire 1 * i1 $end
$var wire 1 ( o $end
$upscope $end
$scope module a2 $end
$var wire 1 ' i0 $end
$var wire 1 / i1 $end
$var wire 1 W o $end
$upscope $end
$scope module o2 $end
$var wire 1 W i0 $end
$var wire 1 , i1 $end
$var wire 1 - o $end
$upscope $end
$upscope $end
$scope module c7_2 $end
$var wire 1 B g0 $end
$var wire 1 - g1 $end
$var wire 1 A p0 $end
$var wire 1 ( p1 $end
$var wire 1 X t $end
$var wire 1 Y p $end
$var wire 1 Z g $end
$scope module a1 $end
$var wire 1 ( i0 $end
$var wire 1 A i1 $end
$var wire 1 Y o $end
$upscope $end
$scope module a2 $end
$var wire 1 ( i0 $end
$var wire 1 B i1 $end
$var wire 1 X o $end
$upscope $end
$scope module o2 $end
$var wire 1 X i0 $end
$var wire 1 - i1 $end
$var wire 1 Z o $end
$upscope $end
$upscope $end
$scope module p_0 $end
$var wire 1 [ x $end
$var wire 1 \ y $end
$var wire 1 4 p $end
$var wire 1 6 g $end
$scope module a $end
$var wire 1 [ i0 $end
$var wire 1 \ i1 $end
$var wire 1 6 o $end
$upscope $end
$scope module o $end
$var wire 1 [ i0 $end
$var wire 1 \ i1 $end
$var wire 1 4 o $end
$upscope $end
$upscope $end
$scope module p_1 $end
$var wire 1 ] x $end
$var wire 1 ^ y $end
$var wire 1 9 p $end
$var wire 1 ; g $end
$scope module a $end
$var wire 1 ] i0 $end
$var wire 1 ^ i1 $end
$var wire 1 ; o $end
$upscope $end
$scope module o $end
$var wire 1 ] i0 $end
$var wire 1 ^ i1 $end
$var wire 1 9 o $end
$upscope $end
$upscope $end
$scope module p_2 $end
$var wire 1 _ x $end
$var wire 1 ` y $end
$var wire 1 > p $end
$var wire 1 ? g $end
$scope module a $end
$var wire 1 _ i0 $end
$var wire 1 ` i1 $end
$var wire 1 ? o $end
$upscope $end
$scope module o $end
$var wire 1 _ i0 $end
$var wire 1 ` i1 $end
$var wire 1 > o $end
$upscope $end
$upscope $end
$scope module p_3 $end
$var wire 1 a x $end
$var wire 1 b y $end
$var wire 1 D p $end
$var wire 1 F g $end
$scope module a $end
$var wire 1 a i0 $end
$var wire 1 b i1 $end
$var wire 1 F o $end
$upscope $end
$scope module o $end
$var wire 1 a i0 $end
$var wire 1 b i1 $end
$var wire 1 D o $end
$upscope $end
$upscope $end
$scope module p_4 $end
$var wire 1 c x $end
$var wire 1 d y $end
$var wire 1 I p $end
$var wire 1 J g $end
$scope module a $end
$var wire 1 c i0 $end
$var wire 1 d i1 $end
$var wire 1 J o $end
$upscope $end
$scope module o $end
$var wire 1 c i0 $end
$var wire 1 d i1 $end
$var wire 1 I o $end
$upscope $end
$upscope $end
$scope module p_5 $end
$var wire 1 e x $end
$var wire 1 f y $end
$var wire 1 O p $end
$var wire 1 P g $end
$scope module a $end
$var wire 1 e i0 $end
$var wire 1 f i1 $end
$var wire 1 P o $end
$upscope $end
$scope module o $end
$var wire 1 e i0 $end
$var wire 1 f i1 $end
$var wire 1 O o $end
$upscope $end
$upscope $end
$scope module p_6 $end
$var wire 1 g x $end
$var wire 1 h y $end
$var wire 1 U p $end
$var wire 1 V g $end
$scope module a $end
$var wire 1 g i0 $end
$var wire 1 h i1 $end
$var wire 1 V o $end
$upscope $end
$scope module o $end
$var wire 1 g i0 $end
$var wire 1 h i1 $end
$var wire 1 U o $end
$upscope $end
$upscope $end
$scope module p_7 $end
$var wire 1 i x $end
$var wire 1 j y $end
$var wire 1 k p $end
$var wire 1 l g $end
$scope module a $end
$var wire 1 i i0 $end
$var wire 1 j i1 $end
$var wire 1 l o $end
$upscope $end
$scope module o $end
$var wire 1 i i0 $end
$var wire 1 j i1 $end
$var wire 1 k o $end
$upscope $end
$upscope $end
$scope module s0 $end
$var wire 1 m i0 $end
$var wire 1 n i1 $end
$var wire 1 $ i2 $end
$var wire 1 o temp $end
$var wire 1 p o $end
$scope module xor2_0 $end
$var wire 1 m i0 $end
$var wire 1 n i1 $end
$var wire 1 o o $end
$upscope $end
$scope module xor2_1 $end
$var wire 1 $ i0 $end
$var wire 1 o i1 $end
$var wire 1 p o $end
$upscope $end
$upscope $end
$scope module s1 $end
$var wire 1 q i0 $end
$var wire 1 r i1 $end
$var wire 1 7 i2 $end
$var wire 1 s temp $end
$var wire 1 t o $end
$scope module xor2_0 $end
$var wire 1 q i0 $end
$var wire 1 r i1 $end
$var wire 1 s o $end
$upscope $end
$scope module xor2_1 $end
$var wire 1 7 i0 $end
$var wire 1 s i1 $end
$var wire 1 t o $end
$upscope $end
$upscope $end
$scope module s2 $end
$var wire 1 u i0 $end
$var wire 1 v i1 $end
$var wire 1 < i2 $end
$var wire 1 w temp $end
$var wire 1 x o $end
$scope module xor2_0 $end
$var wire 1 u i0 $end
$var wire 1 v i1 $end
$var wire 1 w o $end
$upscope $end
$scope module xor2_1 $end
$var wire 1 < i0 $end
$var wire 1 w i1 $end
$var wire 1 x o $end
$upscope $end
$upscope $end
$scope module s3 $end
$var wire 1 y i0 $end
$var wire 1 z i1 $end
$var wire 1 B i2 $end
$var wire 1 { temp $end
$var wire 1 | o $end
$scope module xor2_0 $end
$var wire 1 y i0 $end
$var wire 1 z i1 $end
$var wire 1 { o $end
$upscope $end
$scope module xor2_1 $end
$var wire 1 B i0 $end
$var wire 1 { i1 $end
$var wire 1 | o $end
$upscope $end
$upscope $end
$scope module s4 $end
$var wire 1 } i0 $end
$var wire 1 ~ i1 $end
$var wire 1 G i2 $end
$var wire 1 !" temp $end
$var wire 1 "" o $end
$scope module xor2_0 $end
$var wire 1 } i0 $end
$var wire 1 ~ i1 $end
$var wire 1 !" o $end
$upscope $end
$scope module xor2_1 $end
$var wire 1 G i0 $end
$var wire 1 !" i1 $end
$var wire 1 "" o $end
$upscope $end
$upscope $end
$scope module s5 $end
$var wire 1 #" i0 $end
$var wire 1 $" i1 $end
$var wire 1 M i2 $end
$var wire 1 %" temp $end
$var wire 1 &" o $end
$scope module xor2_0 $end
$var wire 1 #" i0 $end
$var wire 1 $" i1 $end
$var wire 1 %" o $end
$upscope $end
$scope module xor2_1 $end
$var wire 1 M i0 $end
$var wire 1 %" i1 $end
$var wire 1 &" o $end
$upscope $end
$upscope $end
$scope module s6 $end
$var wire 1 '" i0 $end
$var wire 1 (" i1 $end
$var wire 1 S i2 $end
$var wire 1 )" temp $end
$var wire 1 *" o $end
$scope module xor2_0 $end
$var wire 1 '" i0 $end
$var wire 1 (" i1 $end
$var wire 1 )" o $end
$upscope $end
$scope module xor2_1 $end
$var wire 1 S i0 $end
$var wire 1 )" i1 $end
$var wire 1 *" o $end
$upscope $end
$upscope $end
$scope module s7 $end
$var wire 1 +" i0 $end
$var wire 1 ," i1 $end
$var wire 1 Z i2 $end
$var wire 1 -" temp $end
$var wire 1 ." o $end
$scope module xor2_0 $end
$var wire 1 +" i0 $end
$var wire 1 ," i1 $end
$var wire 1 -" o $end
$upscope $end
$scope module xor2_1 $end
$var wire 1 Z i0 $end
$var wire 1 -" i1 $end
$var wire 1 ." o $end
$upscope $end
$upscope $end
$upscope $end
$upscope $end
$enddefinitions $end
#0
$dumpvars
0."
0-"
0,"
0+"
0*"
0)"
0("
0'"
1&"
1%"
1$"
0#"
0""
0!"
0~
0}
1|
1{
1z
0y
0x
0w
0v
0u
0t
0s
0r
0q
1p
1o
1n
0m
0l
0k
0j
0i
0h
0g
1f
0e
0d
0c
1b
0a
0`
0_
0^
0]
1\
0[
0Z
0Y
0X
0W
0V
0U
0T
0S
0R
0Q
0P
1O
0N
0M
0L
0K
0J
0I
0H
0G
0F
0E
1D
0C
0B
0A
0@
0?
0>
0=
0<
0;
0:
09
08
07
06
05
14
03
02
b101001 1
00
0/
0.
0-
0,
0+
0*
0)
0(
0'
b101001 &
b0 %
0$
b101001 #
b0 "
b101001 !
$end
#5
1)
1(
1*
0p
1""
1'
1x
b1111100 !
b1111100 1
1*"
04
1I
0o
1!"
1>
1U
1w
1)"
0\
1d
0f
0n
1~
0$"
1_
1e
1g
1u
1#"
1'"
b11000 #
b11000 &
b1100100 "
b1100100 %
#10
1S
0&"
1.
0)
1M
1N
0(
1+
0*
1t
0|
1."
1/
0'
0""
b11000110 !
b11000110 1
1*"
19
0D
1k
1s
0{
1-"
1J
0U
0!"
0)"
1^
0b
1f
1j
1r
0z
1$"
1,"
1c
0e
0g
1}
0#"
0'"
b10110010 #
b10110010 &
b10100 "
b10100 %
#15
0S
1<
1&"
0.
18
0t
0M
0N
1'
1|
1*"
0."
17
0+
0/
b1101100 !
b1101100 1
1x
1D
1U
0k
1{
1)"
0-"
16
14
0>
0J
0I
0w
1\
1b
0d
0f
1h
0j
1n
1z
0~
0$"
1("
0,"
1[
0_
0c
1e
1m
0u
0}
1#"
b1001011 #
b1001011 &
b100001 "
b100001 %
#20
1."
1Z
1-
0*"
0<
1,
1S
08
1t
1T
1.
0|
1""
0&"
07
1+
b10010110 !
b10010110 1
1x
0D
1I
1P
0{
1!"
0%"
06
04
1>
1w
0\
0b
1d
1f
0h
0n
0z
1~
1$"
0("
0[
1_
1g
0m
1u
1'"
b110010 #
b110010 &
b1100100 "
b1100100 %
#25
1."
1Z
1M
1N
1W
1-
0*"
1/
0""
1)
1(
0,
1S
0+
1H
1G
1*
0T
1.
0x
b10000010 !
b10000010 1
0&"
0>
1F
1D
0P
0w
1%"
0^
1b
0d
0r
1z
0~
1]
0_
1a
1c
0e
1q
0u
1y
1}
0#"
b101000 #
b101000 &
b1011010 "
b1011010 %
#30
0Z
0-
0)
0(
0W
1+
1x
0H
0G
0*
0'
1p
1&"
1*"
b11100111 !
b11100111 1
1."
1>
1J
1w
0!"
14
0F
0D
1P
0U
1k
1o
0%"
0)"
1-"
1^
1`
0b
1d
1r
1v
0z
1~
1[
0]
0a
1e
0g
1i
1m
0q
0y
1#"
0'"
1+"
b110110 #
b110110 &
b10110001 "
b10110001 %
#35
1Z
1-
1""
1)
1(
1W
1H
1G
1*
1'
0p
0&"
0*"
b10010110 !
b10010110 1
1."
04
1F
1D
0P
1U
0k
0o
1%"
1)"
0-"
0^
1b
0r
1z
0[
1]
1a
0e
1g
0i
0m
1q
1y
0#"
1'"
0+"
b111100 #
b111100 &
b1011010 "
b1011010 %
#40
0."
0Z
0-
0(
0W
0+
1p
0x
0""
0'
b1000011 !
b1000011 1
1*"
14
0>
0J
1o
0w
1!"
0U
0)"
1\
1^
0`
0d
1n
1r
0v
0~
0]
0g
0q
0'"
b101011 #
b101011 &
b11000 "
b11000 %
#50
0*"
0S
0M
0.
0/
0N
0)
0t
0&"
0G
0H
0*
b1 !
b1 1
0""
09
0O
0s
0%"
0F
0D
0I
0!"
0^
0b
0f
0r
0z
0$"
0a
0c
0y
0}
b1 #
b1 &
b0 "
b0 %
